{
	"mekanism:excavation_escalation_unit": "mekanism.api.gear.ModuleData",
	"mekanism:farming_unit": "mekanism.api.gear.ModuleData",
	"mekanism:charge_distribution_unit": "mekanism.api.gear.ModuleData",
	"mekanism:energy_unit": "mekanism.api.gear.ModuleData",
	"mekanism:frost_walker_unit": "mekanism.api.gear.ModuleData",
	"mekanism:silk_touch_unit": "mekanism.api.gear.ModuleData",
	"mekanism:color_modulation_unit": "mekanism.api.gear.ModuleData",
	"mekanism:motorized_servo_unit": "mekanism.api.gear.ModuleData",
	"mekanism:fortune_unit": "mekanism.api.gear.ModuleData",
	"mekanism:nutritional_injection_unit": "mekanism.api.gear.ModuleData",
	"mekanism:radiation_shielding_unit": "mekanism.api.gear.ModuleData",
	"mekanism:shearing_unit": "mekanism.api.gear.ModuleData",
	"mekanism:attack_amplification_unit": "mekanism.api.gear.ModuleData",
	"mekanism:inhalation_purification_unit": "mekanism.api.gear.ModuleData",
	"mekanism:locomotive_boosting_unit": "mekanism.api.gear.ModuleData",
	"mekanism:hydraulic_propulsion_unit": "mekanism.api.gear.ModuleData",
	"mekanism:vein_mining_unit": "mekanism.api.gear.ModuleData",
	"mekanismgenerators:solar_recharging_unit": "mekanism.api.gear.ModuleData",
	"mekanismgenerators:geothermal_generator_unit": "mekanism.api.gear.ModuleData",
	"mekanism:gravitational_modulating_unit": "mekanism.api.gear.ModuleData",
	"mekanism:vision_enhancement_unit": "mekanism.api.gear.ModuleData",
	"mekanism:teleportation_unit": "mekanism.api.gear.ModuleData",
	"mekanism:magnetic_attraction_unit": "mekanism.api.gear.ModuleData",
	"mekanism:dosimeter_unit": "mekanism.api.gear.ModuleData",
	"mekanism:hydrostatic_repulsor_unit": "mekanism.api.gear.ModuleData",
	"mekanism:blasting_unit": "mekanism.api.gear.ModuleData",
	"mekanism:geiger_unit": "mekanism.api.gear.ModuleData",
	"mekanism:soul_surfer_unit": "mekanism.api.gear.ModuleData",
	"mekanism:elytra_unit": "mekanism.api.gear.ModuleData",
	"mekanism:gyroscopic_stabilization_unit": "mekanism.api.gear.ModuleData",
	"mekanism:jetpack_unit": "mekanism.api.gear.ModuleData",
	"mekanism:electrolytic_breathing_unit": "mekanism.api.gear.ModuleData",
	"mekanism:laser_dissipation_unit": "mekanism.api.gear.ModuleData"
}